alzheimer_classification/__init__.py
alzheimer_classification/alzheimer_dataset.py
alzheimer_classification/models/__init__.py
alzheimer_classification/models/generic_model.py
alzheimer_classification/models/model_utils.py
alzheimer_classification/models/simple_cnn.py
alzheimer_classification/models/vgg16.py
alzheimer_classification/predict.py
alzheimer_classification/train.py
alzheimer_classification/utils/__init__.py
alzheimer_classification/utils/definitions.py
alzheimer_classification-0.2.0.dist-info/METADATA
alzheimer_classification-0.2.0.dist-info/WHEEL
alzheimer_classification-0.2.0.dist-info/RECORD
