Metadata-Version: 2.1
Name: alzheimer_classification
Version: 0.2.0
Summary: Detecting the stage of Alzheimer's based on MRI images.
Author: s24575
Author-email: sawickigrzegorz66@gmail.com
Requires-Python: >=3.9,<4.0
Classifier: Programming Language :: Python :: 3
Classifier: Programming Language :: Python :: 3.9
Classifier: Programming Language :: Python :: 3.10
Classifier: Programming Language :: Python :: 3.11
Classifier: Programming Language :: Python :: 3.12
Requires-Dist: matplotlib (>=3.9.0,<4.0.0)
Requires-Dist: numpy (<2.0.0)
Requires-Dist: pre-commit (>=3.7.1,<4.0.0)
Requires-Dist: pytorch-lightning (>=2.3.1,<3.0.0)
Requires-Dist: tensorboard (>=2.17.0,<3.0.0)
Requires-Dist: torch (>=2.3.1,<3.0.0)
Requires-Dist: torchvision (>=0.18.1,<0.19.0)
